[
	{
		"classID":"1",
		"imgList":"img/img1.jpg",
		"name":"女装"
	},
	{
		"classID":"2",
		"imgList":"img/img2.jpg",
		"name":"女鞋"
	},
	{
		"classID":"3",
		"imgList":"img/img3.jpg",
		"name":"男装"
	},
	{
		"classID":"4",
		"imgList":"img/img4.jpg",
		"name":"男鞋"
	},
	{
		"classID":"5",
		"imgList":"img/img5.jpg",
		"name":"箱包"
	},
	{
		"classID":"6",
		"imgList":"img/img6.jpg",
		"name":"配饰"
	},
	{
		"classID":"7",
		"imgList":"img/img7.jpg",
		"name":"家居装饰"
	},
	{
		"classID":"8",
		"imgList":"img/img8.jpg",
		"name":"美妆"
	},
	{
		"classID":"9",
		"imgList":"img/img9.jpg",
		"name":"美食"
	},
	{
		"classID":"10",
		"imgList":"img/img10.jpg",
		"name":"数码"
	},
	{
		"classID":"11",
		"imgList":"img/img11.jpg",
		"name":"户外运动"
	},
	{
		"classID":"12",
		"imgList":"img/img12.jpg",
		"name":"礼物"
	},
	{
		"classID":"13",
		"imgList":"img/img13.jpg",
		"name":"日用百货"
	}
]
